{
  "mainSchedule": [
    {
      "days": [
        "Mon",
        "Tue",
        "Wed",
        "Thu",
        "Fri"
      ],
      "schedule": [
        {
          "name": "sat-1",
          "startTime": "23:37",
          "endTime": "23:39",
          "habits": [
            "Attend team meeting"
          ],
          "vibrateOnStart": [
            0,1000,250,1000
          ],
          "vibrateBeforeEnd": [
            0,1000,250,1000,250,1000
          ],
          "vibrateBeforeEndSecs": 60
        },
        {
          "name": "sat-2",
          "startTime": "23:39",
          "endTime": "23:41",
          "habits": [
            "Attend team meeting"
          ],
          "vibrateOnStart": [
            0,1000,250,1000
          ],
          "vibrateBeforeEnd": [
            0,1000,250,1000,250,1000
          ],
          "vibrateBeforeEndSecs": 60
        },
        {
          "name": "sat-3",
          "startTime": "23:41",
          "endTime": "23:43",
          "habits": [
            "Attend team meeting"
          ],
          "vibrateOnStart": [
            0,1000,250,1000
          ],
          "vibrateBeforeEnd": [
            0,1000,250,1000,250,1000
          ],
          "vibrateBeforeEndSecs": 60
        },
        {
          "name": "sat-4",
          "startTime": "23:43",
          "endTime": "23:45",
          "habits": [
            "Attend team meeting"
          ],
          "vibrateOnStart": [
            0,1000,250,1000
          ],
          "vibrateBeforeEnd": [
            0,1000,250,1000,250,1000
          ],
          "vibrateBeforeEndSecs": 60
        },
        {
          "name": "sat-5",
          "startTime": "23:45",
          "endTime": "23:47",
          "habits": [
            "Attend team meeting"
          ],
          "vibrateOnStart": [
            0,1000,250,1000
          ],
          "vibrateBeforeEnd": [
            0,1000,250,1000,250,1000
          ],
          "vibrateBeforeEndSecs": 60
        }
      ]
    },
    {
      "days": [
        "Sat"
      ],
      "schedule": [
        {
          "name": "sat-1",
          "startTime": "04:16",
          "endTime": "04:18",
          "habits": [
            "Attend team meeting"
          ],
          "vibrateOnStart": [
            0,1000,250,5000
          ],
          "vibrateBeforeEnd": [
            0,1000,250,1000,250,1000
          ],
          "vibrateBeforeEndSecs": 60
        },
        {
          "name": "sat-2",
          "startTime": "04:18",
          "endTime": "04:20",
          "habits": [
            "Attend team meeting"
          ],
          "vibrateOnStart": [
            0,1000,250,5000
          ],
          "vibrateBeforeEnd": [
            0,1000,250,1000,250,1000
          ],
          "vibrateBeforeEndSecs": 60
        },
        {
          "name": "sat-3",
          "startTime": "04:20",
          "endTime": "04:22",
          "habits": [
            "Attend team meeting"
          ],
          "vibrateOnStart": [
            0,1000,250,5000
          ],
          "vibrateBeforeEnd": [
            0,1000,250,1000,250,1000
          ],
          "vibrateBeforeEndSecs": 60
        },
        {
          "name": "sat-4",
          "startTime": "04:22",
          "endTime": "04:24",
          "habits": [
            "Attend team meeting"
          ],
          "vibrateOnStart": [
            0,1000,250,5000
          ],
          "vibrateBeforeEnd": [
            0,1000,250,1000,250,1000
          ],
          "vibrateBeforeEndSecs": 60
        },
        {
          "name": "sat-5",
          "startTime": "04:24",
          "endTime": "04:26",
          "habits": [
            "Attend team meeting"
          ],
          "vibrateOnStart": [
            0,1000,250,5000
          ],
          "vibrateBeforeEnd": [
            0,1000,250,1000,250,1000
          ],
          "vibrateBeforeEndSecs": 60
        }
      ]
    },
    {
      "days": [
        "Sun"
      ],
      "schedule": [
        {
          "name": "sat-sun-abc",
          "startTime": "01:00",
          "endTime": "03:55",
          "habits": [
            "Attend team meeting"
          ],
          "vibrateOnStart": [
            500
          ],
          "vibrateBeforeEnd": [
            1000
          ],
          "vibrateBeforeEndSecs": 100
        }
      ]
    }
  ]
}
